Wg_web_client/__init__.py
Wg_web_client/client.py
Wg_web_client/driver_factory.py
Wg_web_client/exceptions.py
wg_web_client-0.1.12.dist-info/licenses/LICENSE
wg_web_client-0.1.12.dist-info/METADATA
wg_web_client-0.1.12.dist-info/WHEEL
wg_web_client-0.1.12.dist-info/top_level.txt
wg_web_client-0.1.12.dist-info/RECORD
