Metadata-Version: 2.4
Name: Wg_web_client
Version: 0.1.12
Summary: WireGuard automation client with async support using Selenium and aiohttp
Author: Zurlex
License-File: LICENSE
Requires-Dist: selenium>=4.0.0
Requires-Dist: webdriver-manager>=4.0.0
Requires-Dist: aiohttp>=3.8.0
Dynamic: author
Dynamic: license-file
Dynamic: requires-dist
Dynamic: summary
